{
    "meta":{
        "status":"success",
        "message":"ok"
    },
    "data":[
        {
            "id":0,
            "longitude":116.368904,
            "latitude":39.923423,
            "title":"宏利同创电脑维修",
            "content":"主营：电脑维修，电脑周边配件，系统维护，网...地址：北京通州区果园环岛葛布店北里10号楼底商",
            "url":"http://ditu.amap.com/detail/B000A8URXB?citycode=110105"
        },
        {
            "id":1,
            "longitude":116.382122,
            "latitude":39.921176,
            "title":"宏利同创电脑维修1",
            "content":"主营：电脑维修，电脑周边配件，系统维护，网...地址：北京通州区果园环岛葛布店北里10号楼底商",
            "url":"http://ditu.amap.com/detail/B000A8URXB?citycode=110105"
        },
        {
            "id":2,
            "longitude":116.387271,
            "latitude":39.922501,
            "title":"宏利同创电脑维修2",
            "content":"主营：电脑维修，电脑周边配件，系统维护，网...地址：北京通州区果园环岛葛布店北里10号楼底商",
            "url":"http://ditu.amap.com/detail/B000A8URXB?citycode=110105"
        },
        {
            "id":3,
            "longitude":116.398258,
            "latitude":39.914600,
            "title":"宏利同创电脑维修3",
            "content":"主营：电脑维修，电脑周边配件，系统维护，网...地址：北京通州区果园环岛葛布店北里10号楼底商",
            "url":"http://ditu.amap.com/detail/B000A8URXB?citycode=110105"
        },
        {
            "id":4,
            "longitude":116.368914,
            "latitude":39.913600,
            "title":"宏利同创电脑维修4",
            "content":"主营：电脑维修，电脑周边配件，系统维护，网...地址：北京通州区果园环岛葛布店北里10号楼底商",
            "url":"http://ditu.amap.com/detail/B000A8URXB?citycode=110105"
        },
        {
            "id":5,
            "longitude":116.368204,
            "latitude":39.921376,
            "title":"宏利同创电脑维修5",
            "content":"主营：电脑维修，电脑周边配件，系统维护，网...地址：北京通州区果园环岛葛布店北里10号楼底商",
            "url":"http://ditu.amap.com/detail/B000A8URXB?citycode=110105"
        },
        {
            "id":6,
            "longitude":116.368404,
            "latitude":39.926176,
            "title":"宏利同创电脑维修6",
            "content":"主营：电脑维修，电脑周边配件，系统维护，网...地址：北京通州区果园环岛葛布店北里10号楼底商",
            "url":"http://ditu.amap.com/detail/B000A8URXB?citycode=110105"
        },
        {
            "id":7,
            "longitude":116.365904,
            "latitude":39.921106,
            "title":"宏利同创电脑维修7",
            "content":"主营：电脑维修，电脑周边配件，系统维护，网...地址：北京通州区果园环岛葛布店北里10号楼底商",
            "url":"http://ditu.amap.com/detail/B000A8URXB?citycode=110105"
        },
        {
            "id":8,
            "longitude":116.361904,
            "latitude":39.922106,
            "title":"宏利同创电脑维修8",
            "content":"主营：电脑维修，电脑周边配件，系统维护，网...地址：北京通州区果园环岛葛布店北里10号楼底商",
            "url":"http://ditu.amap.com/detail/B000A8URXB?citycode=110105"
        },
        {
            "id":9,
            "longitude":116.368504,
            "latitude":39.924076,
            "title":"宏利同创电脑维修9",
            "content":"主营：电脑维修，电脑周边配件，系统维护，网...地址：北京通州区果园环岛葛布店北里10号楼底商",
            "url":"http://ditu.amap.com/detail/B000A8URXB?citycode=110105"
        }
    ]
}
